conficus/__init__.py
conficus/coerce.py
conficus/exceptions.py
conficus/format.py
conficus/inherit.py
conficus/readonly.py
conficus/structs.py
conficus/walk.py
conficus-1.0.0.dist-info/METADATA
conficus-1.0.0.dist-info/WHEEL
conficus-1.0.0.dist-info/RECORD
