Metadata-Version: 2.3
Name: conficus
Version: 1.0.0
Summary: python toml configuration library
License: MIT
Author: Mark Gemmill
Author-email: dev@markgemmill.com
Requires-Python: >=3.11.0
Classifier: Development Status :: 5 - Production/Stable
Classifier: Intended Audience :: Developers
Classifier: License :: OSI Approved :: MIT License
Classifier: Programming Language :: Python :: 3
Classifier: Programming Language :: Python :: 3.11
Classifier: Programming Language :: Python :: 3.12
Classifier: Programming Language :: Python :: 3.13
Classifier: Topic :: Software Development :: Libraries :: Python Modules
Requires-Dist: tomlkit (>=0.13.3,<0.14.0)
Project-URL: Homepage, https://github.com/markgemmill/conficus
